glue_heatmap/__init__.py
glue_heatmap/coords.py
glue_heatmap/layer_artist.py
glue_heatmap/menubar_plugin.py
glue_heatmap/run_sample.py
glue_heatmap/state.py
glue_heatmap/viewer.py
glue_heatmap/qt/__init__.py
glue_heatmap/qt/data_viewer.py
glue_heatmap/qt/extract_to_matrix.py
glue_heatmap/qt/extract_to_matrix.ui
glue_heatmap/qt/layer_style_editor.py
glue_heatmap/qt/layer_style_editor.ui
glue_heatmap/qt/layer_style_editor_subset.py
glue_heatmap/qt/layer_style_editor_subset.ui
glue_heatmap/qt/options_widget.py
glue_heatmap/qt/options_widget.ui
glue_heatmap/qt/subset_to_data.ui
glue_heatmap/qt/subset_tool.py
glue_heatmap/qt/tests/__init__.py
glue_heatmap/qt/tests/test_heatmap.py
glue_heatmap-2.1.1.dist-info/METADATA
glue_heatmap-2.1.1.dist-info/WHEEL
glue_heatmap-2.1.1.dist-info/entry_points.txt
glue_heatmap-2.1.1.dist-info/top_level.txt
glue_heatmap-2.1.1.dist-info/RECORD
