Metadata-Version: 2.2
Name: glue-heatmap
Version: 2.1.1
Summary: A Heatmap viewer
Home-page: https://www.gluesolutions.io
Author: glue solutions, inc.
Author-email: jfoster@gluesolutions.io
Classifier: Intended Audience :: Science/Research
Classifier: Operating System :: OS Independent
Classifier: Programming Language :: Python
Classifier: Programming Language :: Python :: 3
Classifier: Programming Language :: Python :: 3.8
Classifier: Programming Language :: Python :: 3.9
Classifier: Programming Language :: Python :: 3.10
Classifier: Programming Language :: Python :: 3.11
Classifier: Topic :: Scientific/Engineering :: Visualization
Classifier: License :: OSI Approved :: BSD License
Requires-Python: >=3.8
Requires-Dist: glue-core
Requires-Dist: glue-qt
Requires-Dist: scipy
Provides-Extra: test
Requires-Dist: pytest; extra == "test"
Requires-Dist: pytest-qt; extra == "test"
Requires-Dist: pytest-faulthandler; extra == "test"
Requires-Dist: mock; extra == "test"
Provides-Extra: qt
Requires-Dist: PyQt6; extra == "qt"
Provides-Extra: glue
Requires-Dist: glue-core; extra == "glue"
Requires-Dist: glue-qt; extra == "glue"
